matprops/__init__.py
matprops/config.py
matprops/layouts.py
matprops/props.py
matprops/utils.py
matprops-1.0.4.5.dist-info/licenses/LICENSE
matprops-1.0.4.5.dist-info/METADATA
matprops-1.0.4.5.dist-info/WHEEL
matprops-1.0.4.5.dist-info/top_level.txt
matprops-1.0.4.5.dist-info/RECORD
