Metadata-Version: 2.4
Name: matprops
Version: 1.0.4.5
Summary: Python library written on top of matplotlib library for customizable proportional charts
Home-page: https://github.com/shammeer-s/matprops
Author: Mohammed Shammeer
Author-email: mohammedshammeer.s@gmail.com
Keywords: matplotlib,visualization,proportional charts
Classifier: Programming Language :: Python :: 3
Classifier: Development Status :: 3 - Alpha
Classifier: Intended Audience :: Developers
Classifier: Topic :: Software Development :: Build Tools
Classifier: License :: OSI Approved :: MIT License
Classifier: Operating System :: OS Independent
License-File: LICENSE
Requires-Dist: numpy~=2.2.6
Requires-Dist: pandas~=2.2.3
Requires-Dist: matplotlib~=3.10.3
Provides-Extra: dev
Requires-Dist: pytest>=6.2.5; extra == "dev"
Dynamic: author
Dynamic: author-email
Dynamic: classifier
Dynamic: description
Dynamic: description-content-type
Dynamic: home-page
Dynamic: keywords
Dynamic: license-file
Dynamic: provides-extra
Dynamic: requires-dist
Dynamic: summary
